thu_learn_downloader/__init__.py
thu_learn_downloader/_version.py
thu_learn_downloader/_version.pyi
thu_learn_downloader/main.py
thu_learn_downloader/py.typed
thu_learn_downloader/client/__init__.py
thu_learn_downloader/client/client.py
thu_learn_downloader/client/course.py
thu_learn_downloader/client/document.py
thu_learn_downloader/client/homework.py
thu_learn_downloader/client/learn.py
thu_learn_downloader/client/model.py
thu_learn_downloader/client/semester.py
thu_learn_downloader/client/url.py
thu_learn_downloader/common/__init__.py
thu_learn_downloader/common/logging.py
thu_learn_downloader/common/typing.py
thu_learn_downloader/download/__init__.py
thu_learn_downloader/download/description.py
thu_learn_downloader/download/downloader.py
thu_learn_downloader/download/filename.py
thu_learn_downloader/download/selector.py
thu_learn_downloader/download/style.py
thu_learn_downloader/login/__init__.py
thu_learn_downloader/login/auto.py
thu_learn_downloader/login/bitwarden.py
thu_learn_downloader/login/browser.py
thu_learn_downloader-0.4.1.dist-info/METADATA
thu_learn_downloader-0.4.1.dist-info/WHEEL
thu_learn_downloader-0.4.1.dist-info/entry_points.txt
thu_learn_downloader-0.4.1.dist-info/licenses/LICENSE
thu_learn_downloader-0.4.1.dist-info/RECORD
