Metadata-Version: 2.4
Name: thu-learn-downloader
Version: 0.4.1
Summary: Download everything from Web Learning of Tsinghua University
Project-URL: Changelog, https://github.com/liblaf/thu-learn-downloader/blob/main/CHANGELOG.md
Project-URL: Documentation, https://liblaf.github.io/thu-learn-downloader/
Project-URL: Funding, https://github.com/liblaf/thu-learn-downloader?sponsor=1
Project-URL: Homepage, https://github.com/liblaf/thu-learn-downloader
Project-URL: Issue Tracker, https://github.com/liblaf/thu-learn-downloader/issues
Project-URL: Release Notes, https://github.com/liblaf/thu-learn-downloader/releases
Project-URL: Source Code, https://github.com/liblaf/thu-learn-downloader
Author-email: liblaf <30631553+liblaf@users.noreply.github.com>
License-Expression: MIT
License-File: LICENSE
Classifier: Development Status :: 4 - Beta
Classifier: Intended Audience :: Developers
Classifier: License :: OSI Approved
Classifier: License :: OSI Approved :: MIT License
Classifier: Operating System :: OS Independent
Classifier: Programming Language :: Python
Classifier: Programming Language :: Python :: 3
Classifier: Programming Language :: Python :: 3.12
Classifier: Programming Language :: Python :: 3.13
Classifier: Typing :: Typed
Requires-Python: >=3.12
Requires-Dist: beautifulsoup4<5,>=4.0.0
Requires-Dist: lazy-loader<0.5,>=0.4.0
Requires-Dist: loguru<0.8,>=0.7.0
Requires-Dist: pydantic<3,>=2.0.0
Requires-Dist: python-dateutil<3,>=2.0.0
Requires-Dist: requests<3,>=2.0.0
Requires-Dist: rich<15,>=14.0.0
Requires-Dist: selenium<5,>=4.0.0
Requires-Dist: tenacity<10,>=9.0.0
Requires-Dist: typer<0.17,>=0.16.0
